buxi_proba
